pyJStrobe/__init__.py
pyJStrobe/process_manager.py
pyJStrobe-0.1.dist-info/LICENSE
pyJStrobe-0.1.dist-info/METADATA
pyJStrobe-0.1.dist-info/WHEEL
pyJStrobe-0.1.dist-info/top_level.txt
pyJStrobe-0.1.dist-info/RECORD
