Metadata-Version: 2.1
Name: pyJStrobe
Version: 0.1
Summary: This package is used to automate the DES application jStrobe.
Author: Joseph Louis
Author-email: joseph.louis@oregonstate.edu
Requires-Python: >=3.6
License-File: LICENSE
